fairgbm/VERSION.txt
fairgbm/__init__.py
fairgbm/basic.py
fairgbm/callback.py
fairgbm/compat.py
fairgbm/dask.py
fairgbm/engine.py
fairgbm/lib_lightgbm.so
fairgbm/libpath.py
fairgbm/plotting.py
fairgbm/sklearn.py
fairgbm-0.9.14.dist-info/LICENSE
fairgbm-0.9.14.dist-info/METADATA
fairgbm-0.9.14.dist-info/WHEEL
fairgbm-0.9.14.dist-info/top_level.txt
fairgbm-0.9.14.dist-info/RECORD
